azuresearchta.py
azure_search_ta-0.3.0.dist-info/LICENSE
azure_search_ta-0.3.0.dist-info/METADATA
azure_search_ta-0.3.0.dist-info/WHEEL
azure_search_ta-0.3.0.dist-info/entry_points.txt
azure_search_ta-0.3.0.dist-info/top_level.txt
azure_search_ta-0.3.0.dist-info/RECORD
