Metadata-Version: 2.1
Name: azure-search-ta
Version: 0.3.0
Summary: Azure Search Test Analyzer API Client Tool
Home-page: https://github.com/yokawasa/azure-search-ta
Author: Yoichi Kawasaki
Author-email: yoichi.kawasaki@outlook.com
License: MIT
Download-URL: https://pypi.python.org/pypi/azure-seatch-ta
Keywords: azure search azuresearch text analysis api
Platform: any
Classifier: Environment :: Console
Classifier: Intended Audience :: Developers
Classifier: Intended Audience :: System Administrators
Classifier: License :: OSI Approved :: MIT License
Classifier: Programming Language :: Python :: 2.7
Classifier: Programming Language :: Python :: 3
Classifier: Programming Language :: Python :: 3.3
Classifier: Programming Language :: Python :: 3.4
Classifier: Programming Language :: Python :: 3.5
Classifier: Programming Language :: Python :: 3.6
Classifier: Topic :: Utilities
Requires-Dist: argparse
Requires-Dist: simplejson
Requires-Dist: beautifulsoup4
